wapi/__init__.py
wapi/wapi.py
wapi_trade-0.0.4.dist-info/LICENSE
wapi_trade-0.0.4.dist-info/METADATA
wapi_trade-0.0.4.dist-info/WHEEL
wapi_trade-0.0.4.dist-info/top_level.txt
wapi_trade-0.0.4.dist-info/RECORD
